README.md
setup.py
sgi.py
scrap_google_images.egg-info/PKG-INFO
scrap_google_images.egg-info/SOURCES.txt
scrap_google_images.egg-info/dependency_links.txt
scrap_google_images.egg-info/entry_points.txt
scrap_google_images.egg-info/requires.txt
scrap_google_images.egg-info/top_level.txt