Metadata-Version: 1.2
Name: scrap-google-images
Version: 1.0.0
Summary: scrap/download google images
Home-page: UNKNOWN
Author: Akhil Lawrence
Author-email: akhilputhiry@gmail.com
License: MIT
Keywords: download scrap google images
Platform: UNKNOWN
Classifier: Development Status :: 5 - Production/Stable
Classifier: Intended Audience :: Developers
Classifier: Topic :: Internet
Classifier: Topic :: Utilities
Classifier: License :: Freely Distributable
Classifier: Programming Language :: Python :: 2.7
Requires-Python: >2.6
